test/__init__.py
test/run_benchmarks.py
test/run_tests.py
veros/__init__.py
veros/_version.py
veros/backend.py
veros/decorators.py
veros/handlers.py
veros/settings.py
veros/time.py
veros/timer.py
veros/variables.py
veros/veros.py
veros/veros_legacy.py
veros/cli/__init__.py
veros/cli/veros.py
veros/cli/veros_copy_setup.py
veros/cli/veros_create_mask.py
veros/cli/veros_resubmit.py
veros/core/__init__.py
veros/core/advection.py
veros/core/cyclic.py
veros/core/diffusion.py
veros/core/eke.py
veros/core/friction.py
veros/core/idemix.py
veros/core/momentum.py
veros/core/numerics.py
veros/core/thermodynamics.py
veros/core/tke.py
veros/core/utilities.py
veros/core/density/__init__.py
veros/core/density/get_rho.py
veros/core/density/gsw.py
veros/core/density/linear_eq.py
veros/core/density/nonlinear_eq1.py
veros/core/density/nonlinear_eq2.py
veros/core/density/nonlinear_eq3.py
veros/core/external/__init__.py
veros/core/external/island.py
veros/core/external/solve_poisson.py
veros/core/external/solve_stream.py
veros/core/external/streamfunction_init.py
veros/core/external/utilities.py
veros/core/isoneutral/__init__.py
veros/core/isoneutral/diffusion.py
veros/core/isoneutral/friction.py
veros/core/isoneutral/isoneutral.py
veros/core/special/__init__.py
veros/core/special/tdma_opencl.py
veros/diagnostics/__init__.py
veros/diagnostics/averages.py
veros/diagnostics/cfl_monitor.py
veros/diagnostics/diagnostic.py
veros/diagnostics/energy.py
veros/diagnostics/overturning.py
veros/diagnostics/snapshot.py
veros/diagnostics/tracer_monitor.py
veros/diagnostics/io_tools/__init__.py
veros/diagnostics/io_tools/hdf5.py
veros/diagnostics/io_tools/netcdf.py
veros/setup/__init__.py
veros/setup/acc/__init__.py
veros/setup/acc/acc.py
veros/setup/eady/__init__.py
veros/setup/eady/eady.py
veros/setup/global_1deg/__init__.py
veros/setup/global_1deg/assets.yml
veros/setup/global_1deg/global_one_degree.py
veros-0.1.1.dist-info/DESCRIPTION.rst
veros-0.1.1.dist-info/METADATA
veros-0.1.1.dist-info/RECORD
veros-0.1.1.dist-info/WHEEL
veros-0.1.1.dist-info/entry_points.txt
veros-0.1.1.dist-info/metadata.json
veros-0.1.1.dist-info/top_level.txt
