Metadata-Version: 2.0
Name: veros
Version: 0.1.1
Summary: The versatile ocean simulator, in pure Python, powered by Bohrium.
Home-page: https://veros.readthedocs.io
Author: Dion Häfner (NBI Copenhagen)
Author-email: mail@dionhaefner.de
License: MIT
Keywords: oceanography python parallel numpy multi-core geophysics ocean-model bohrium
Platform: UNKNOWN
Classifier: Development Status :: 3 - Alpha
Classifier: Intended Audience :: Science/Research
Classifier: License :: OSI Approved :: MIT License
Classifier: Programming Language :: Python :: 2
Classifier: Programming Language :: Python :: 2.7
Classifier: Programming Language :: Python :: 3
Classifier: Programming Language :: Python :: 3.4
Classifier: Programming Language :: Python :: 3.5
Classifier: Programming Language :: Python :: 3.6
Classifier: Programming Language :: Python :: Implementation :: CPython
Classifier: Topic :: Scientific/Engineering
Classifier: Operating System :: Microsoft :: Windows
Classifier: Operating System :: POSIX
Classifier: Operating System :: Unix
Classifier: Operating System :: MacOS
Requires-Dist: click
Requires-Dist: requests
Requires-Dist: numpy (>=1.13)
Requires-Dist: scipy
Requires-Dist: netCDF4
Requires-Dist: h5py
Requires-Dist: pillow
Requires-Dist: ruamel.yaml
Requires-Dist: backports.functools-lru-cache
Requires-Dist: future
Provides-Extra: all
Requires-Dist: bohrium; extra == 'all'
Requires-Dist: matplotlib; extra == 'all'
Requires-Dist: pyamg; extra == 'all'
Requires-Dist: pyinstrument; extra == 'all'
Requires-Dist: pyopencl; extra == 'all'
Requires-Dist: versioneer; extra == 'all'
Requires-Dist: xarray; extra == 'all'
Provides-Extra: bohrium
Requires-Dist: bohrium; extra == 'bohrium'
Provides-Extra: dev
Requires-Dist: pyinstrument; extra == 'dev'
Requires-Dist: versioneer; extra == 'dev'
Provides-Extra: fast
Requires-Dist: bohrium; extra == 'fast'
Requires-Dist: pyamg; extra == 'fast'
Provides-Extra: gpu
Requires-Dist: bohrium; extra == 'gpu'
Requires-Dist: pyopencl; extra == 'gpu'
Provides-Extra: postprocessing
Requires-Dist: xarray; extra == 'postprocessing'
Requires-Dist: matplotlib; extra == 'postprocessing'
